suvtk/__init__.py
suvtk/__main__.py
suvtk/cli.py
suvtk/co_occurrence.py
suvtk/comments.py
suvtk/data/genome_types.tsv
suvtk/data/segmented_viruses.tsv
suvtk/download_database.py
suvtk/features.py
suvtk/gbk2tbl.py
suvtk/helper_scripts/get_genome_types.R
suvtk/helper_scripts/get_segmented_viruses.R
suvtk/table2asn.py
suvtk/taxonomy.py
suvtk/utils.py
suvtk/virus_info.py
suvtk-0.1.6.dist-info/WHEEL
suvtk-0.1.6.dist-info/entry_points.txt
suvtk-0.1.6.dist-info/METADATA
suvtk-0.1.6.dist-info/RECORD
