Metadata-Version: 2.3
Name: suvtk
Version: 0.1.6
Summary: Tool to submit viral sequences to Genbank.
Author: Lander De Coninck
License: Apache-2.0
Classifier: License :: OSI Approved :: Apache Software License
Requires-Dist: biopython>=1.83
Requires-Dist: click
Requires-Dist: numpy>1.24.4
Requires-Dist: pandas>=2.0.3
Requires-Dist: pyrodigal-gv>=0.3.2
Requires-Dist: requests>=2.32.3
Requires-Dist: scipy>=1.13.1
Requires-Dist: taxopy>=0.14.0
Requires-Dist: pytest ; extra == 'test'
Requires-Python: >=3.9
Project-URL: CI, https://github.com/LanderDC/suvtk/actions
Project-URL: Changelog, https://github.com/LanderDC/suvtk/releases
Project-URL: Homepage, https://github.com/LanderDC/suvtk
Project-URL: Issues, https://github.com/LanderDC/suvtk/issues
Provides-Extra: test
